pyhoma/__init__.py
pyhoma/client.py
pyhoma/const.py
pyhoma/enums.py
pyhoma/exceptions.py
pyhoma/models.py
pyhoma_localpatch-0.5.20.dist-info/LICENSE
pyhoma_localpatch-0.5.20.dist-info/WHEEL
pyhoma_localpatch-0.5.20.dist-info/METADATA
pyhoma_localpatch-0.5.20.dist-info/RECORD
