Metadata-Version: 2.1
Name: pyhoma-localpatch
Version: 0.5.20
Summary: Async Python wrapper to interact with internal Somfy TaHoma API, or other OverKiz API's.
Home-page: https://github.com/iMicknl/python-tahoma-api
License: MIT
Author: Mick Vleeshouwer
Requires-Python: >=3.7,<4.0
Classifier: License :: OSI Approved :: MIT License
Classifier: Programming Language :: Python :: 3
Classifier: Programming Language :: Python :: 3.10
Classifier: Programming Language :: Python :: 3.7
Classifier: Programming Language :: Python :: 3.8
Classifier: Programming Language :: Python :: 3.9
Requires-Dist: aiohttp (>=3.6.1,<4.0.0)
Requires-Dist: backoff (>=1.10.0,<2.0.0)
Requires-Dist: pyhumps (>=1.3.1,<2.0.0)
Project-URL: Repository, https://github.com/iMicknl/python-tahoma-api
